sportgems-0.8.0.dist-info/METADATA
sportgems-0.8.0.dist-info/WHEEL
sportgems/__init__.pyi
sportgems/plot_on_map.py
sportgems/__init__.py
sportgems/sportgems.cpython-39-darwin.so
sportgems-0.8.0.dist-info/RECORD
