Metadata-Version: 2.1
Name: sportgems
Version: 0.8.0
Summary: Find valuable gems 💎 in your tracked sport 🚴 activity!
Keywords: sports activity parser rust sports-data
Home-Page: https://github.com/fgebhart/sportgems
Author: Fabian Gebhart
License: MIT
Requires-Python: >=3.8
